bits/__init__.py
bits/gaia/__init__.py
bits/gaia/archibus.py
bits/gaia/atlassian.py
bits/gaia/auth.py
bits/gaia/aws.py
bits/gaia/azure.py
bits/gaia/mysql.py
bits/gaia/okta.py
bits/gaia/redis.py
bits/gaia/sendgrid.py
bits/gaia/slack.py
bits/gaia/ssh.py
bits/gaia/workday.py
bits_gaia-0.5.8.dist-info/METADATA
bits_gaia-0.5.8.dist-info/WHEEL
bits_gaia-0.5.8.dist-info/top_level.txt
bits_gaia-0.5.8.dist-info/RECORD
