Metadata-Version: 2.1
Name: bits-gaia
Version: 0.5.8
Summary: BITS Gaia
Author: Lukas Karlsson
Author-email: karlsson@broadinstitute.org
License: Apache Software License
Platform: UNKNOWN
Requires-Dist: google-cloud-secret-manager
Requires-Dist: google-cloud-storage
Requires-Dist: pyyaml
